README.rst
setup.py
mdptree/__init__.py
mdptree/graphs.py
mdptree/mdp.py
mdptree/utils.py
mdptree.egg-info/PKG-INFO
mdptree.egg-info/SOURCES.txt
mdptree.egg-info/dependency_links.txt
mdptree.egg-info/top_level.txt