Metadata-Version: 1.1
Name: mdptree
Version: 0.1
Summary: Tools to model Markov Decision Processes
Home-page: http://pchanial.github.com/mdptree
Author: Pierre Chanial
Author-email: pchanial@aneo.fr
License: UNKNOWN
Keywords: statistics
Platform: MacOS X
Platform: Linux
Platform: Solaris
Platform: Unix
Platform: Windows
Classifier: Programming Language :: Python
Classifier: Programming Language :: Python :: 3
Classifier: Programming Language :: Python :: 3.5
Classifier: Development Status :: 4 - Beta
Classifier: Intended Audience :: Science/Research
Classifier: Operating System :: OS Independent
Classifier: Topic :: Scientific/Engineering
